lctoolkit/__init__.py
lctoolkit/base.py
lc_toolkit-0.0.1.dist-info/LICENSE
lc_toolkit-0.0.1.dist-info/METADATA
lc_toolkit-0.0.1.dist-info/WHEEL
lc_toolkit-0.0.1.dist-info/top_level.txt
lc_toolkit-0.0.1.dist-info/RECORD
