Metadata-Version: 2.1
Name: lc-toolkit
Version: 0.0.1
Summary: LC Toolkit
Home-page: https://github.com/pypa/sampleproject
Author: Markus Wahle
Author-email: markus.wahle@gmx.de
License: UNKNOWN
Project-URL: Bug Tracker, https://github.com/pypa/sampleproject/issues
Platform: UNKNOWN
Classifier: Programming Language :: Python :: 3
Classifier: License :: OSI Approved :: GNU General Public License v3 or later (GPLv3+)
Classifier: Operating System :: OS Independent
Requires-Python: >=3.6
License-File: LICENSE
